pynlcontrol/BasicUtils.py
pynlcontrol/Controller.py
pynlcontrol/Estimator.py
pynlcontrol/QPInterface.py
pynlcontrol/__init__.py
pynlcontrol/external/qpOASES.zip
pynlcontrol/templates/GenCode_c.j2
pynlcontrol/templates/GenCode_h.j2
pynlcontrol/templates/Gen_Mex_c.j2
pynlcontrol/templates/MHE_DataCollect.j2
pynlcontrol/templates/TestCode.j2
pynlcontrol/templates/qpOASES_c.j2
pynlcontrol/templates/qpOASES_h.j2
pyNLControl-0.0.19.dist-info/LICENSE
pyNLControl-0.0.19.dist-info/METADATA
pyNLControl-0.0.19.dist-info/WHEEL
pyNLControl-0.0.19.dist-info/top_level.txt
pyNLControl-0.0.19.dist-info/RECORD
