Metadata-Version: 2.1
Name: pyNLControl
Version: 0.0.19
Summary: Package for non-linear control and estimation.
Home-page: https://github.com/NiranjanBhujel/pyNLControl
Author: Niranjan Bhujel
Author-email: niranjan.bhujel2014@gmail.com
License: UNKNOWN
Project-URL: Bug Tracker, https://github.com/NiranjanBhujel/pyNLControl/issues
Platform: UNKNOWN
Classifier: Programming Language :: Python :: 3
Classifier: License :: OSI Approved :: MIT License
Classifier: Operating System :: OS Independent
Requires-Python: >=3.6
License-File: LICENSE
Requires-Dist: casadi
Requires-Dist: jinja2
